{"id":"ec1d2268-8d2b-44ec-a9da-549c7287ef86","revision":0,"last_node_id":10,"last_link_id":14,"nodes":[{"id":7,"type":"PreviewImage","pos":[1774.2586669921875,290.68341064453125],"size":[545.3455200195312,611.9698486328125],"flags":{},"order":9,"mode":0,"inputs":[{"localized_name":"이미지","name":"images","type":"IMAGE","link":9}],"outputs":[],"properties":{"cnr_id":"comfy-core","ver":"0.3.43","Node name for S&R":"PreviewImage","widget_ue_connectable":{}},"widgets_values":[]},{"id":8,"type":"LoadImage","pos":[-198.3270721435547,630.2957763671875],"size":[270,314],"flags":{},"order":0,"mode":0,"inputs":[{"localized_name":"이미지","name":"image","type":"COMBO","widget":{"name":"image"},"link":null},{"localized_name":"업로드할 파일 선택","name":"upload","type":"IMAGEUPLOAD","widget":{"name":"upload"},"link":null}],"outputs":[{"localized_name":"이미지","name":"IMAGE","type":"IMAGE","links":[10]},{"localized_name":"마스크","name":"MASK","type":"MASK","links":null}],"properties":{"cnr_id":"comfy-core","ver":"0.3.43","Node name for S&R":"LoadImage","widget_ue_connectable":{}},"widgets_values":["Gemini_Generated_Image_qg6kewqg6kewqg6k.png","image"]},{"id":9,"type":"VAEEncode","pos":[290.529296875,628.6214599609375],"size":[162.06790161132812,46],"flags":{},"order":6,"mode":0,"inputs":[{"localized_name":"픽셀 이미지","name":"pixels","type":"IMAGE","link":10},{"localized_name":"vae","name":"vae","type":"VAE","link":14}],"outputs":[{"localized_name":"잠재 데이터","name":"LATENT","type":"LATENT","links":[11]}],"properties":{"cnr_id":"comfy-core","ver":"0.3.43","Node name for S&R":"VAEEncode","widget_ue_connectable":{}},"widgets_values":[]},{"id":1,"type":"CheckpointLoaderSimple","pos":[71.41312408447266,333.1894226074219],"size":[270,98],"flags":{},"order":1,"mode":0,"inputs":[{"localized_name":"체크포인트 파일명","name":"ckpt_name","type":"COMBO","widget":{"name":"ckpt_name"},"link":null}],"outputs":[{"localized_name":"모델","name":"MODEL","type":"MODEL","links":[1]},{"localized_name":"CLIP","name":"CLIP","type":"CLIP","links":[2,3]},{"localized_name":"VAE","name":"VAE","type":"VAE","links":[4]}],"properties":{"cnr_id":"comfy-core","ver":"0.3.43","Node name for S&R":"CheckpointLoaderSimple","widget_ue_connectable":{}},"widgets_values":["architectureUrbanSdlife_v60.safetensors"]},{"id":5,"type":"VAEDecode","pos":[1579.927001953125,94.3769302368164],"size":[140,46],"flags":{},"order":8,"mode":0,"inputs":[{"localized_name":"잠재 데이터","name":"samples","type":"LATENT","link":8},{"localized_name":"vae","name":"vae","type":"VAE","link":4}],"outputs":[{"localized_name":"이미지","name":"IMAGE","type":"IMAGE","links":[9]}],"properties":{"cnr_id":"comfy-core","ver":"0.3.43","Node name for S&R":"VAEDecode","widget_ue_connectable":{}},"widgets_values":[]},{"id":4,"type":"CLIPTextEncode","pos":[575.1630859375,-44.09944152832031],"size":[833.56787109375,524.8115844726562],"flags":{},"order":4,"mode":0,"inputs":[{"localized_name":"clip","name":"clip","type":"CLIP","link":2},{"localized_name":"프롬프트 텍스트","name":"text","type":"STRING","widget":{"name":"text"},"link":null}],"outputs":[{"localized_name":"조건","name":"CONDITIONING","type":"CONDITIONING","links":[6]}],"properties":{"cnr_id":"comfy-core","ver":"0.3.43","Node name for S&R":"CLIPTextEncode","widget_ue_connectable":{}},"widgets_values":["highly detailed, ultra realistic, cinematic lighting, moody, night city, glowing windows,\nstreet lights reflecting on wet pavement, distant skyscrapers,\nsubtle architectural alterations, modern building facades, neon glow,\ndeep shadows, (night:1.3), (dark:1.2), beautiful, photorealistic, 8k\n<lora:add_detail:0.8> <lora:more_details:0.8>",[false,true]],"color":"#232","bgcolor":"#353"},{"id":3,"type":"CLIPTextEncode","pos":[568.0715942382812,553.9302978515625],"size":[852.732666015625,509.4889221191406],"flags":{},"order":5,"mode":0,"inputs":[{"localized_name":"clip","name":"clip","type":"CLIP","link":3},{"localized_name":"프롬프트 텍스트","name":"text","type":"STRING","widget":{"name":"text"},"link":null}],"outputs":[{"localized_name":"조건","name":"CONDITIONING","type":"CONDITIONING","links":[7]}],"properties":{"cnr_id":"comfy-core","ver":"0.3.43","Node name for S&R":"CLIPTextEncode","widget_ue_connectable":{}},"widgets_values":["daylight, sunlight, bright sky, oversaturated, blurry, low resolution, bad quality,\nugly, deformed, disfigured, poor lighting, cartoon, illustration, drawing, sketch,\nexcessive noise, artifacts, watermark, signature",[false,true]],"color":"#322","bgcolor":"#533"},{"id":2,"type":"KSampler","pos":[1456.3621826171875,258.3765869140625],"size":[270,262],"flags":{},"order":7,"mode":0,"inputs":[{"localized_name":"모델","name":"model","type":"MODEL","link":1},{"localized_name":"긍정 조건","name":"positive","type":"CONDITIONING","link":6},{"localized_name":"부정 조건","name":"negative","type":"CONDITIONING","link":7},{"localized_name":"잠재 데이터","name":"latent_image","type":"LATENT","link":11},{"localized_name":"시드","name":"seed","type":"INT","widget":{"name":"seed"},"link":null},{"localized_name":"스텝 수","name":"steps","type":"INT","widget":{"name":"steps"},"link":null},{"localized_name":"cfg","name":"cfg","type":"FLOAT","widget":{"name":"cfg"},"link":null},{"localized_name":"샘플러 이름","name":"sampler_name","type":"COMBO","widget":{"name":"sampler_name"},"link":null},{"localized_name":"스케줄러","name":"scheduler","type":"COMBO","widget":{"name":"scheduler"},"link":null},{"localized_name":"노이즈 제거양","name":"denoise","type":"FLOAT","widget":{"name":"denoise"},"link":null}],"outputs":[{"localized_name":"잠재 데이터","name":"LATENT","type":"LATENT","links":[8]}],"properties":{"cnr_id":"comfy-core","ver":"0.3.43","Node name for S&R":"KSampler","widget_ue_connectable":{}},"widgets_values":[265201834829787,"randomize",55,7.5,"dpmpp_2m_sde_gpu","karras",0.4000000000000001]},{"id":10,"type":"VAELoader","pos":[173.81240844726562,739.9929809570312],"size":[270,58],"flags":{},"order":2,"mode":0,"inputs":[{"localized_name":"vae 파일명","name":"vae_name","type":"COMBO","widget":{"name":"vae_name"},"link":null}],"outputs":[{"localized_name":"VAE","name":"VAE","type":"VAE","links":[14]}],"properties":{"cnr_id":"comfy-core","ver":"0.3.43","Node name for S&R":"VAELoader","widget_ue_connectable":{}},"widgets_values":["vaeFtMse840000EmaPruned_vaeFtMse840k.safetensors"]},{"id":6,"type":"EmptyLatentImage","pos":[178.69271850585938,1038.308349609375],"size":[270,106],"flags":{},"order":3,"mode":0,"inputs":[{"localized_name":"너비","name":"width","type":"INT","widget":{"name":"width"},"link":null},{"localized_name":"높이","name":"height","type":"INT","widget":{"name":"height"},"link":null},{"localized_name":"배치 크기","name":"batch_size","type":"INT","widget":{"name":"batch_size"},"link":null}],"outputs":[{"localized_name":"잠재 데이터","name":"LATENT","type":"LATENT","links":[]}],"properties":{"cnr_id":"comfy-core","ver":"0.3.43","Node name for S&R":"EmptyLatentImage","widget_ue_connectable":{}},"widgets_values":[1280,720,1]}],"links":[[1,1,0,2,0,"MODEL"],[2,1,1,4,0,"CLIP"],[3,1,1,3,0,"CLIP"],[4,1,2,5,1,"VAE"],[6,4,0,2,1,"CONDITIONING"],[7,3,0,2,2,"CONDITIONING"],[8,2,0,5,0,"LATENT"],[9,5,0,7,0,"IMAGE"],[10,8,0,9,0,"IMAGE"],[11,9,0,2,3,"LATENT"],[14,10,0,9,1,"VAE"]],"groups":[],"config":{},"extra":{"ue_links":[],"ds":{"scale":0.43056764313424944,"offset":[701.0590974088568,847.1507753016934]},"links_added_by_ue":[]},"version":0.4}